falco/__init__.py
falco/__version__.py
falco/client.py
falco/client_credentials.py
falco/errors.py
falco/domain/__init__.py
falco/domain/common.py
falco/domain/outputs.py
falco/domain/version.py
falco/schema/__init__.py
falco/schema/outputs_pb2.py
falco/schema/schema_pb2.py
falco/schema/version_pb2.py
falco/svc/__init__.py
falco/svc/outputs_pb2_grpc.py
falco/svc/schema_pb2_grpc.py
falco/svc/version_pb2_grpc.py
tests/__init__.py
tests/conftest.py
tests/mock.py
tests/test_client.py
tests/domain/__init__.py
tests/domain/test_outputs.py
tests/domain/test_version.py
falco-0.4.0.dist-info/LICENSE
falco-0.4.0.dist-info/METADATA
falco-0.4.0.dist-info/WHEEL
falco-0.4.0.dist-info/top_level.txt
falco-0.4.0.dist-info/RECORD
