Metadata-Version: 2.1
Name: falco
Version: 0.4.0
Summary: Python client and SDK for Falco.
Home-page: https://github.com/falcosecurity/client-py
Author: The Falco Authors
Author-email: cncf-falco-dev@lists.cncf.io
License: Apache 2.0
Platform: UNKNOWN
Classifier: Development Status :: 3 - Alpha
Classifier: License :: OSI Approved :: Apache Software License
Classifier: Programming Language :: Python
Classifier: Programming Language :: Python :: 3
Classifier: Programming Language :: Python :: 3.6
Classifier: Programming Language :: Python :: 3.7
Classifier: Programming Language :: Python :: 3.8
Classifier: Programming Language :: Python :: Implementation :: CPython
Classifier: Programming Language :: Python :: Implementation :: PyPy
Requires-Python: >=3.6
License-File: LICENSE
Requires-Dist: grpcio (==1.26.0)
Requires-Dist: python-dateutil (==2.8.1)
Requires-Dist: protobuf (==3.12.2)
